web_downloader/__init__.py
web_downloader/clean_env.py
web_downloader/create_db.py
web_downloader/process_url.py
web_downloader/lib/__init__.py
web_downloader/lib/db.py
web_downloader/lib/download_webpage.py
web_downloader/lib/get_firefox_driver.py
web_downloader/lib/parse_webpage.py
web_downloader/lib/paths_management.py
web_downloader-0.0.8.dist-info/LICENSE
web_downloader-0.0.8.dist-info/METADATA
web_downloader-0.0.8.dist-info/WHEEL
web_downloader-0.0.8.dist-info/top_level.txt
web_downloader-0.0.8.dist-info/RECORD
